optdash/__init__.py
optdash/plot_data.py
optdash/server.py
optdash/study.py
optdash/version.py
optdash/frontend/public/bundle.js
optdash/frontend/public/index.html
optdash/frontend/public/manifest.json
tests/__init__.py
optdash-0.0.2.dist-info/LICENSE
optdash-0.0.2.dist-info/METADATA
optdash-0.0.2.dist-info/WHEEL
optdash-0.0.2.dist-info/entry_points.txt
optdash-0.0.2.dist-info/top_level.txt
optdash-0.0.2.dist-info/RECORD
